LICENSE
MANIFEST.in
README.rst
runtests.py
setup.py
django_sabridge.egg-info/PKG-INFO
django_sabridge.egg-info/SOURCES.txt
django_sabridge.egg-info/dependency_links.txt
django_sabridge.egg-info/requires.txt
django_sabridge.egg-info/top_level.txt
django_sabridge.egg-info/zip-safe
docs/.gitignore
docs/Makefile
docs/api.rst
docs/api.rst~
docs/conf.py
docs/index.rst
docs/license.rst
docs/license.rst~
docs/make.bat
sabridge/__init__.py
sabridge/base.py
sabridge/version.py
tests/__init__.py
tests/models.py
tests/tests/__init__.py
tests/tests/test_base.py