Metadata-Version: 1.0
Name: django-sabridge
Version: 0.0.1
Summary: Provides SQLAlchemy access to Django models.
Home-page: http://github.com/johnpaulett/django-sabridge
Author: John Paulett
Author-email: john@paulett.org
License: UNKNOWN
Platform: UNKNOWN
Classifier: Framework :: Django
Classifier: Intended Audience :: Developers
Classifier: Operating System :: OS Independent
Classifier: Topic :: Database
Classifier: Topic :: Software Development
